CHANGES
LICENSE
MANIFEST.in
README.rst
run_tests.py
setup.cfg
setup.py
ibm_db_sa/__init__.py
ibm_db_sa/base.py
ibm_db_sa/ibm_db.py
ibm_db_sa/pyodbc.py
ibm_db_sa/reflection.py
ibm_db_sa/requirements.py
ibm_db_sa/zxjdbc.py
ibm_db_sa_py3.egg-info/PKG-INFO
ibm_db_sa_py3.egg-info/SOURCES.txt
ibm_db_sa_py3.egg-info/dependency_links.txt
ibm_db_sa_py3.egg-info/entry_points.txt
ibm_db_sa_py3.egg-info/not-zip-safe
ibm_db_sa_py3.egg-info/requires.txt
ibm_db_sa_py3.egg-info/top_level.txt
test/__init__.py
test/test_out_parameters.py
test/test_suite.py