Metadata-Version: 1.1
Name: ibm-db-sa-py3
Version: 0.3.0-1
Summary: SQLAlchemy support for IBM Data Servers
Home-page: http://pypi.python.org/pypi/ibm_db_sa/
Author: IBM Application Development Team
Author-email: opendev@us.ibm.com
License: Apache License 2.0
Download-URL: http://code.google.com/p/ibm-db/downloads/list
Keywords: sqlalchemy database interface IBM Data Servers DB2 Informix IDS
Platform: All
Classifier: Development Status :: 4 - Beta
Classifier: Intended Audience :: Developers
Classifier: License :: OSI Approved :: Apache Software License
Classifier: Operating System :: OS Independent
Classifier: Topic :: Database :: Front-Ends
